pico/__init__.py
pico/client.py
pico/decorators.py
pico/exceptions.py
pico/pico.min.js
pico/pragmaticjson.py
pico/server.py
pico/wrappers.py
pico/extras/__init__.py
pico/extras/sentry.py
pico-2.0.5.dist-info/METADATA
pico-2.0.5.dist-info/WHEEL
pico-2.0.5.dist-info/pbr.json
pico-2.0.5.dist-info/top_level.txt
pico-2.0.5.dist-info/RECORD
