Metadata-Version: 2.1
Name: pico
Version: 2.0.5
Summary: Pico HTTP API Framework
Home-page: http://github.com/fergalwalsh/pico
Author: Fergal Walsh
Author-email: UNKNOWN
License: UNKNOWN
Download-URL: https://github.com/fergalwalsh/pico/tarball/2.0.5
Platform: UNKNOWN
Classifier: Programming Language :: Python
Classifier: Programming Language :: Python :: 2.7
Classifier: Programming Language :: Python :: 3
Requires-Dist: wrapt (>=1.8.0)
Requires-Dist: Werkzeug (>=0.12.1)
Requires-Dist: requests (>=2.9.1)
